CHANGELOG.md
LICENSE
MANIFEST.in
README.md
setup.py
imap_checker/__init__.py
imap_checker/imap_checker.py
imap_checker/logconfig.py
imap_checker.egg-info/PKG-INFO
imap_checker.egg-info/SOURCES.txt
imap_checker.egg-info/dependency_links.txt
imap_checker.egg-info/entry_points.txt
imap_checker.egg-info/not-zip-safe
imap_checker.egg-info/requires.txt
imap_checker.egg-info/top_level.txt