Metadata-Version: 1.0
Name: imap-checker
Version: 0.1.0
Summary: Check you imap inbox for new mails and notifies in your desktop
Home-page: https://github.com/VITIMan/imap-checker
Author: Victoriano Navarro
Author-email: vitiman@gmail.com
License: LICENSE
Keywords: imap,notify,email,imap-checker
Platform: UNKNOWN
